labgraph/__init__.py
labgraph/data/__init__.py
labgraph/data/actors.py
labgraph/data/nodes.py
labgraph/data/sample.py
labgraph/utils/__init__.py
labgraph/utils/data_objects.py
labgraph/utils/db_lock.py
labgraph/utils/dev.py
labgraph/utils/graph.py
labgraph/utils/plot.py
labgraph/utils/config/__init__.py
labgraph/utils/config/config.py
labgraph/views/__init__.py
labgraph/views/actors.py
labgraph/views/base.py
labgraph/views/graph_integrity.py
labgraph/views/nodes.py
labgraph/views/sample.py
tests/__init__.py
tests/conftest.py
tests/test_actors.py
tests/test_nodes.py
tests/test_samples.py
tests/fixtures/__init__.py
tests/fixtures/example_data.py
tests/fixtures/example_system.py
labgraph_db-0.2.1.dist-info/METADATA
labgraph_db-0.2.1.dist-info/WHEEL
labgraph_db-0.2.1.dist-info/top_level.txt
labgraph_db-0.2.1.dist-info/RECORD
