Metadata-Version: 2.1
Name: labgraph-db
Version: 0.2.1
Summary: A library for storing experimental materials science data as graphs using MongoDB.
Download-URL: https://github.com/rekumar/labgraph
Author: Rishi E Kumar
Author-email: re.kumar@icloud.com
License: MIT
Keywords: materials,science,machine,automation,data,mongodb,storage
Classifier: Programming Language :: Python :: 3.8
Classifier: Programming Language :: Python :: 3.9
Classifier: Programming Language :: Python :: 3.10
Classifier: Intended Audience :: Science/Research
Classifier: Operating System :: OS Independent
Classifier: Topic :: Scientific/Engineering :: Information Analysis
Classifier: Topic :: Software Development :: Libraries :: Python Modules
Requires-Python: >=3.8
Requires-Dist: pymongo (>=3.11.2)
Requires-Dist: networkx (>=2.6)
Requires-Dist: numpy (>=1.23.0)
Requires-Dist: matplotlib (>=3.5.2)
Requires-Dist: toml
Requires-Dist: pydantic
Requires-Dist: scipy
Provides-Extra: dev
Requires-Dist: sphinx (>=3.2.1) ; extra == 'dev'
Requires-Dist: sphinx-book-theme (==0.1.7) ; extra == 'dev'
Requires-Dist: recommonmark (~=0.7.1) ; extra == 'dev'
Requires-Dist: sphinx-autodoc-typehints (>=1.12.0) ; extra == 'dev'
Requires-Dist: pytest (>=6.2.5) ; extra == 'dev'
Requires-Dist: pytest-reraise (>=2.1.1) ; extra == 'dev'
Requires-Dist: pylint (>=2.11.1) ; extra == 'dev'
Requires-Dist: pytest-env (~=0.6.2) ; extra == 'dev'
